shader_workshop/__init__.py
shader_workshop/frag.py
shader_workshop/server.py
shader_workshop/tool.py
shader_workshop/frag-examples/intro.frag
shader_workshop/frag-examples/mouse.frag
shader_workshop/frag-examples/noise.frag
shader_workshop/frag-examples/shape.frag
shader_workshop/frag-examples/srgb.glsl
shader_workshop/www/favicon.ico
shader_workshop/www/index.html
shader_workshop/www/shader.js
shader_workshop/www/style.css
shader_workshop-0.6.0.dist-info/licenses/LICENSE
shader_workshop-0.6.0.dist-info/METADATA
shader_workshop-0.6.0.dist-info/WHEEL
shader_workshop-0.6.0.dist-info/entry_points.txt
shader_workshop-0.6.0.dist-info/top_level.txt
shader_workshop-0.6.0.dist-info/RECORD
